parser.py
gimp_recipescraper-0.0.1.dist-info/licenses/LICENSE.txt
gimp_recipescraper-0.0.1.dist-info/METADATA
gimp_recipescraper-0.0.1.dist-info/WHEEL
gimp_recipescraper-0.0.1.dist-info/top_level.txt
gimp_recipescraper-0.0.1.dist-info/RECORD
