Metadata-Version: 2.4
Name: gimp_recipescraper
Version: 0.0.1
Summary: Scrape minecraft recipe from site
Author-email: "Alex H.K." <alex12@gmail.com>
License: MIT License
Classifier: Programming Language :: Python :: 3
Classifier: Operating System :: OS Independent
Requires-Python: >=3.10
License-File: LICENSE.txt
Requires-Dist: requests>=2.32.3
Requires-Dist: beautifulsoup4>=4.12.3
Requires-Dist: pandas>=2.2.3
Dynamic: license-file
